[
  {
    "test": "login-mobile",
    "status": "PASS",
    "detail": "inputs:2, buttons:6, overflow:false"
  },
  {
    "test": "tutor-mobile",
    "status": "PASS",
    "detail": "hScroll:false, sidebar:true, minFont:9px"
  },
  {
    "test": "teacher-mobile",
    "status": "FAIL",
    "detail": "hScroll:false, tabsOverflow:true, buttons:12"
  },
  {
    "test": "admin-mobile",
    "status": "FAIL",
    "detail": "hScroll:false, tabsOverflow:true, buttons:22"
  },
  {
    "test": "dashboard-mobile",
    "status": "PASS",
    "detail": "hScroll:false"
  },
  {
    "test": "navbar-mobile",
    "status": "FAIL",
    "detail": "hamburger:false"
  },
  {
    "test": "touch-targets-mobile",
    "status": "WARN",
    "detail": "total:13, tooSmall:1 — Informativa Privacy(132x19)"
  },
  {
    "test": "login-tablet",
    "status": "PASS",
    "detail": "inputs:2, buttons:6, overflow:false"
  },
  {
    "test": "tutor-tablet",
    "status": "PASS",
    "detail": "hScroll:false, sidebar:true, minFont:9px"
  },
  {
    "test": "teacher-tablet",
    "status": "FAIL",
    "detail": "hScroll:false, tabsOverflow:true, buttons:12"
  },
  {
    "test": "admin-tablet",
    "status": "PASS",
    "detail": "hScroll:false, tabsOverflow:false, buttons:22"
  },
  {
    "test": "dashboard-tablet",
    "status": "PASS",
    "detail": "hScroll:false"
  },
  {
    "test": "navbar-tablet",
    "status": "PASS",
    "detail": "nav:true, links:4"
  },
  {
    "test": "login-desktop",
    "status": "PASS",
    "detail": "inputs:2, buttons:6, overflow:false"
  },
  {
    "test": "tutor-desktop",
    "status": "PASS",
    "detail": "hScroll:false, sidebar:false, minFont:9px"
  },
  {
    "test": "teacher-desktop",
    "status": "PASS",
    "detail": "hScroll:false, tabsOverflow:false, buttons:12"
  },
  {
    "test": "admin-desktop",
    "status": "PASS",
    "detail": "hScroll:false, tabsOverflow:false, buttons:22"
  },
  {
    "test": "dashboard-desktop",
    "status": "PASS",
    "detail": "hScroll:false"
  },
  {
    "test": "navbar-desktop",
    "status": "PASS",
    "detail": "nav:true, links:4"
  }
]